chimed/__init__.py
chimed/__main__.py
chimed/__version__.py
chimed/bell.py
chimed/cli.py
chimed/config.py
chimed/daemon.py
chimed/subcommands.py
chimed/utils.py
chimed/_data/defaults.toml
chimed/_data/audio/paulmorek-beep-03-single.wav
chimed/_data/audio/paulmorek-beep-04-positive.wav
chimed/_data/audio/paulmorek-click-02-double.wav
chimed/_data/audio/paulmorek-click-02-single.wav
chimed/_data/audio/paulmorek-swish-01.wav
chimed/_data/audio/richcraft-chime-4.wav
chimed/_data/audio/stubb-typewriter-ding.wav
chimed/_data/audio/ueffects-e-key.wav
chimed/_data/audio/ueffects-l-key.wav
chimed/_data/audio/ueffects-s-key.wav
chimed-0.1.1.dist-info/CC-BY-3.0.txt
chimed-0.1.1.dist-info/CC0-1.0.txt
chimed-0.1.1.dist-info/GPL-3.0-or-later.txt
chimed-0.1.1.dist-info/METADATA
chimed-0.1.1.dist-info/WHEEL
chimed-0.1.1.dist-info/entry_points.txt
chimed-0.1.1.dist-info/top_level.txt
chimed-0.1.1.dist-info/zip-safe
chimed-0.1.1.dist-info/RECORD
