Metadata-Version: 2.1
Name: chimed
Version: 0.1.1
Summary: Wind chime for your UNIX environment
Home-page: https://github.com/drybjed/chimed
Download-URL: https://github.com/drybjed/chimed/archive/v0.1.1.tar.gz
Author: Maciej Delmanowski
Author-email: drybjed@gmail.com
License: GPL-3.0-or-later
Keywords: audio chime
Classifier: Development Status :: 3 - Alpha
Classifier: Environment :: Console
Classifier: Environment :: No Input/Output (Daemon)
Classifier: Intended Audience :: End Users/Desktop
Classifier: Intended Audience :: Information Technology
Classifier: License :: OSI Approved :: GNU General Public License v3 or later (GPLv3+)
Classifier: Natural Language :: English
Classifier: Operating System :: POSIX
Classifier: Programming Language :: Python
Classifier: Programming Language :: Python :: 3
Classifier: Programming Language :: Python :: 3.5
Classifier: Programming Language :: Python :: 3.6
Classifier: Programming Language :: Python :: 3.7
Classifier: Programming Language :: Python :: 3.8
Classifier: Programming Language :: Python :: 3.9
Classifier: Topic :: Multimedia :: Sound/Audio
Classifier: Topic :: Utilities
Requires-Python: >=2.7, !=3.0.*, !=3.1.*, !=3.2.*, !=3.3.*, !=3.4.*, <4
License-File: LICENSES/CC-BY-3.0.txt
License-File: LICENSES/CC0-1.0.txt
License-File: LICENSES/GPL-3.0-or-later.txt
Requires-Dist: jinja2
Requires-Dist: numpy
Requires-Dist: python-dotenv
Requires-Dist: pyxdg
Requires-Dist: pyyaml
Requires-Dist: simpleaudio
Requires-Dist: soundfile
Requires-Dist: toml
